quantuminspire/__init__.py
quantuminspire/cli/__init__.py
quantuminspire/cli/command_list.py
quantuminspire/py.typed
quantuminspire/sdk/__init__.py
quantuminspire/sdk/models/__init__.py
quantuminspire/sdk/models/base_algorithm.py
quantuminspire/sdk/models/circuit.py
quantuminspire/sdk/models/cqasm_algorithm.py
quantuminspire/sdk/models/file_algorithm.py
quantuminspire/sdk/models/hybrid_algorithm.py
quantuminspire/sdk/models/job_options.py
quantuminspire/sdk/quantum_interface.py
quantuminspire/util/__init__.py
quantuminspire/util/api/__init__.py
quantuminspire/util/api/base_backend.py
quantuminspire/util/api/local_backend.py
quantuminspire/util/api/quantum_interface.py
quantuminspire/util/api/remote_backend.py
quantuminspire/util/authentication.py
quantuminspire/util/configuration.py
quantuminspire/util/connections.py
quantuminspire-3.5.1.dist-info/LICENSE.md
quantuminspire-3.5.1.dist-info/METADATA
quantuminspire-3.5.1.dist-info/WHEEL
quantuminspire-3.5.1.dist-info/entry_points.txt
quantuminspire-3.5.1.dist-info/RECORD
