Metadata-Version: 2.1
Name: quantuminspire
Version: 3.5.1
Summary: SDK for the Quantum Inspire platform.
Home-page: https://www.quantum-inspire.com
License: Apache-2.0
Author: Quantum Inspire
Author-email: support@quantum-inspire.com
Requires-Python: >=3.10,<3.14
Classifier: Development Status :: 4 - Beta
Classifier: License :: OSI Approved :: Apache Software License
Classifier: Programming Language :: Python :: 3
Classifier: Programming Language :: Python :: 3.10
Classifier: Programming Language :: Python :: 3.11
Classifier: Programming Language :: Python :: 3.12
Classifier: Programming Language :: Python :: 3.13
Provides-Extra: local
Requires-Dist: oauthlib (>=3.2.2,<4.0.0)
Requires-Dist: opensquirrel (==0.8.0)
Requires-Dist: pydantic (>=2.10.6,<3.0.0)
Requires-Dist: pydantic-settings (>=2.7.1,<3.0.0)
Requires-Dist: pyjwt (>=2.10.1,<3.0.0)
Requires-Dist: qi-compute-api-client (>=0.50.0,<0.51.0)
Requires-Dist: qiskit (>=2.0.0,<2.2.0)
Requires-Dist: qxelarator (>=0.7.4,<0.11.0) ; extra == "local"
Requires-Dist: requests (>=2.32.3,<3.0.0)
Requires-Dist: typer[all] (>=0.15.1,<0.22.0)
Project-URL: Repository, https://github.com/qutech-delft/quantuminspire
